py2tf/ds_select.py
py2tf/jars/aws-java-sdk-1.7.4.jar
py2tf/jars/hadoop-aws-2.7.5.jar
py2tf/jars/spark-tensorflow-connector_2.11-1.6.0.jar
pysp2tfdemo-0.1.dist-info/DESCRIPTION.rst
pysp2tfdemo-0.1.dist-info/METADATA
pysp2tfdemo-0.1.dist-info/RECORD
pysp2tfdemo-0.1.dist-info/WHEEL
pysp2tfdemo-0.1.dist-info/metadata.json
pysp2tfdemo-0.1.dist-info/top_level.txt
