Metadata-Version: 2.0
Name: pysp2tfdemo
Version: 0.1
Summary: PySpark and TF demo
Home-page: https://github.com/anfeng/py-demo
Author: Andy Feng
Author-email: andy.feng@gmail.com
License: Apache 2.0
Keywords: tensorflow,spark
Platform: UNKNOWN
Classifier: Development Status :: 4 - Beta
Classifier: Intended Audience :: Developers
Classifier: Intended Audience :: Science/Research
Classifier: License :: OSI Approved :: Apache Software License
Classifier: Topic :: Software Development :: Libraries
Classifier: Programming Language :: Python :: 2
Classifier: Programming Language :: Python :: 2.7
Classifier: Programming Language :: Python :: 3
Classifier: Programming Language :: Python :: 3.5
Classifier: Programming Language :: Python :: 3.6
